algods/__init__.py
algods/search.py
algods/validation.py
algods-0.2.0.dist-info/LICENSE
algods-0.2.0.dist-info/METADATA
algods-0.2.0.dist-info/WHEEL
algods-0.2.0.dist-info/top_level.txt
algods-0.2.0.dist-info/RECORD
