Metadata-Version: 2.1
Name: algods
Version: 0.2.0
Summary: A Python package for data structures and algorithms
Home-page: https://github.com/UniquePython/Algods
Author: Ananyo Bhattacharya
Author-email: ananyobhattacharya10@gmail.com
Classifier: Programming Language :: Python :: 3
Classifier: License :: OSI Approved :: MIT License
Classifier: Operating System :: OS Independent
Requires-Python: >=3.8
License-File: LICENSE
